{
  "transcript": "He waded into the edge of the water and began scrubbing himself.",
  "words": [
    {
      "alignedWord": "he",
      "case": "success",
      "end": 0.94,
      "endOffset": 2,
      "phones": [
        {
          "duration": 0.1,
          "phone": "hh_B"
        },
        {
          "duration": 0.09,
          "phone": "iy_E"
        }
      ],
      "start": 0.75,
      "startOffset": 0,
      "word": "He"
    },
    {
      "alignedWord": "<unk>",
      "case": "success",
      "end": 1.21,
      "endOffset": 8,
      "phones": [
        {
          "duration": 0.27,
          "phone": "oov_S"
        }
      ],
      "start": 0.94,
      "startOffset": 3,
      "word": "waded"
    },
    {
      "alignedWord": "into",
      "case": "success",
      "end": 1.43,
      "endOffset": 13,
      "phones": [
        {
          "duration": 0.01,
          "phone": "ih_B"
        },
        {
          "duration": 0.1,
          "phone": "n_I"
        },
        {
          "duration": 0.06,
          "phone": "t_I"
        },
        {
          "duration": 0.05,
          "phone": "ah_E"
        }
      ],
      "start": 1.21,
      "startOffset": 9,
      "word": "into"
    },
    {
      "alignedWord": "the",
      "case": "success",
      "end": 1.6199999999999999,
      "endOffset": 17,
      "phones": [
        {
          "duration": 0.07,
          "phone": "dh_B"
        },
        {
          "duration": 0.12,
          "phone": "iy_E"
        }
      ],
      "start": 1.43,
      "startOffset": 14,
      "word": "the"
    },
    {
      "alignedWord": "edge",
      "case": "success",
      "end": 1.9200000000000002,
      "endOffset": 22,
      "phones": [
        {
          "duration": 0.15,
          "phone": "eh_B"
        },
        {
          "duration": 0.15,
          "phone": "jh_E"
        }
      ],
      "start": 1.62,
      "startOffset": 18,
      "word": "edge"
    },
    {
      "alignedWord": "of",
      "case": "success",
      "end": 2.09,
      "endOffset": 25,
      "phones": [
        {
          "duration": 0.08,
          "phone": "ah_B"
        },
        {
          "duration": 0.08,
          "phone": "v_E"
        }
      ],
      "start": 1.93,
      "startOffset": 23,
      "word": "of"
    },
    {
      "alignedWord": "the",
      "case": "success",
      "end": 2.17,
      "endOffset": 29,
      "phones": [
        {
          "duration": 0.01,
          "phone": "dh_B"
        },
        {
          "duration": 0.07,
          "phone": "ah_E"
        }
      ],
      "start": 2.09,
      "startOffset": 26,
      "word": "the"
    },
    {
      "alignedWord": "water",
      "case": "success",
      "end": 2.6,
      "endOffset": 35,
      "phones": [
        {
          "duration": 0.07,
          "phone": "w_B"
        },
        {
          "duration": 0.15,
          "phone": "ao_I"
        },
        {
          "duration": 0.08,
          "phone": "t_I"
        },
        {
          "duration": 0.13,
          "phone": "er_E"
        }
      ],
      "start": 2.17,
      "startOffset": 30,
      "word": "water"
    },
    {
      "alignedWord": "and",
      "case": "success",
      "end": 2.75,
      "endOffset": 39,
      "phones": [
        {
          "duration": 0.07,
          "phone": "ae_B"
        },
        {
          "duration": 0.04,
          "phone": "n_I"
        },
        {
          "duration": 0.04,
          "phone": "d_E"
        }
      ],
      "start": 2.6,
      "startOffset": 36,
      "word": "and"
    },
    {
      "alignedWord": "began",
      "case": "success",
      "end": 3.24,
      "endOffset": 45,
      "phones": [
        {
          "duration": 0.04,
          "phone": "b_B"
        },
        {
          "duration": 0.07,
          "phone": "ih_I"
        },
        {
          "duration": 0.1,
          "phone": "g_I"
        },
        {
          "duration": 0.17,
          "phone": "ae_I"
        },
        {
          "duration": 0.11,
          "phone": "n_E"
        }
      ],
      "start": 2.75,
      "startOffset": 40,
      "word": "began"
    },
    {
      "alignedWord": "scrubbing",
      "case": "success",
      "end": 3.71,
      "endOffset": 55,
      "phones": [
        {
          "duration": 0.12,
          "phone": "s_B"
        },
        {
          "duration": 0.07,
          "phone": "k_I"
        },
        {
          "duration": 0.06,
          "phone": "r_I"
        },
        {
          "duration": 0.05,
          "phone": "ah_I"
        },
        {
          "duration": 0.05,
          "phone": "b_I"
        },
        {
          "duration": 0.05,
          "phone": "ih_I"
        },
        {
          "duration": 0.07,
          "phone": "ng_E"
        }
      ],
      "start": 3.24,
      "startOffset": 46,
      "word": "scrubbing"
    },
    {
      "alignedWord": "himself",
      "case": "success",
      "end": 4.27,
      "endOffset": 63,
      "phones": [
        {
          "duration": 0.03,
          "phone": "hh_B"
        },
        {
          "duration": 0.05,
          "phone": "ih_I"
        },
        {
          "duration": 0.06,
          "phone": "m_I"
        },
        {
          "duration": 0.08,
          "phone": "s_I"
        },
        {
          "duration": 0.1,
          "phone": "eh_I"
        },
        {
          "duration": 0.08,
          "phone": "l_I"
        },
        {
          "duration": 0.16,
          "phone": "f_E"
        }
      ],
      "start": 3.71,
      "startOffset": 56,
      "word": "himself"
    }
  ]
}