{
  "transcript": "Each day she became a more vital part of him.",
  "words": [
    {
      "alignedWord": "each",
      "case": "success",
      "end": 0.76,
      "endOffset": 4,
      "phones": [
        {
          "duration": 0.17,
          "phone": "iy_B"
        },
        {
          "duration": 0.1,
          "phone": "ch_E"
        }
      ],
      "start": 0.49,
      "startOffset": 0,
      "word": "Each"
    },
    {
      "alignedWord": "day",
      "case": "success",
      "end": 0.99,
      "endOffset": 8,
      "phones": [
        {
          "duration": 0.1,
          "phone": "d_B"
        },
        {
          "duration": 0.13,
          "phone": "ey_E"
        }
      ],
      "start": 0.76,
      "startOffset": 5,
      "word": "day"
    },
    {
      "alignedWord": "she",
      "case": "success",
      "end": 1.09,
      "endOffset": 12,
      "phones": [
        {
          "duration": 0.09,
          "phone": "sh_B"
        },
        {
          "duration": 0.01,
          "phone": "iy_E"
        }
      ],
      "start": 0.99,
      "startOffset": 9,
      "word": "she"
    },
    {
      "alignedWord": "became",
      "case": "success",
      "end": 1.37,
      "endOffset": 19,
      "phones": [
        {
          "duration": 0.07,
          "phone": "b_B"
        },
        {
          "duration": 0.04,
          "phone": "iy_I"
        },
        {
          "duration": 0.07,
          "phone": "k_I"
        },
        {
          "duration": 0.07,
          "phone": "ey_I"
        },
        {
          "duration": 0.01,
          "phone": "m_E"
        }
      ],
      "start": 1.11,
      "startOffset": 13,
      "word": "became"
    },
    {
      "alignedWord": "a",
      "case": "success",
      "end": 1.3800000000000001,
      "endOffset": 21,
      "phones": [
        {
          "duration": 0.01,
          "phone": "ah_S"
        }
      ],
      "start": 1.37,
      "startOffset": 20,
      "word": "a"
    },
    {
      "alignedWord": "more",
      "case": "success",
      "end": 1.68,
      "endOffset": 26,
      "phones": [
        {
          "duration": 0.09,
          "phone": "m_B"
        },
        {
          "duration": 0.12,
          "phone": "ao_I"
        },
        {
          "duration": 0.09,
          "phone": "r_E"
        }
      ],
      "start": 1.38,
      "startOffset": 22,
      "word": "more"
    },
    {
      "alignedWord": "vital",
      "case": "success",
      "end": 2.01,
      "endOffset": 32,
      "phones": [
        {
          "duration": 0.09,
          "phone": "v_B"
        },
        {
          "duration": 0.07,
          "phone": "ay_I"
        },
        {
          "duration": 0.03,
          "phone": "t_I"
        },
        {
          "duration": 0.06,
          "phone": "ah_I"
        },
        {
          "duration": 0.07,
          "phone": "l_E"
        }
      ],
      "start": 1.69,
      "startOffset": 27,
      "word": "vital"
    },
    {
      "alignedWord": "part",
      "case": "success",
      "end": 2.3299999999999996,
      "endOffset": 37,
      "phones": [
        {
          "duration": 0.09,
          "phone": "p_B"
        },
        {
          "duration": 0.08,
          "phone": "aa_I"
        },
        {
          "duration": 0.08,
          "phone": "r_I"
        },
        {
          "duration": 0.07,
          "phone": "t_E"
        }
      ],
      "start": 2.01,
      "startOffset": 33,
      "word": "part"
    },
    {
      "alignedWord": "of",
      "case": "success",
      "end": 2.53,
      "endOffset": 40,
      "phones": [
        {
          "duration": 0.14,
          "phone": "ah_B"
        },
        {
          "duration": 0.06,
          "phone": "v_E"
        }
      ],
      "start": 2.3299999999999996,
      "startOffset": 38,
      "word": "of"
    },
    {
      "alignedWord": "him",
      "case": "success",
      "end": 2.84,
      "endOffset": 44,
      "phones": [
        {
          "duration": 0.06,
          "phone": "hh_B"
        },
        {
          "duration": 0.08,
          "phone": "ih_I"
        },
        {
          "duration": 0.17,
          "phone": "m_E"
        }
      ],
      "start": 2.53,
      "startOffset": 41,
      "word": "him"
    }
  ]
}