{
  "transcript": "But he no longer cared quite so much for that form of diversion.",
  "words": [
    {
      "alignedWord": "but",
      "case": "success",
      "end": 0.84,
      "endOffset": 3,
      "phones": [
        {
          "duration": 0.09,
          "phone": "b_B"
        },
        {
          "duration": 0.07,
          "phone": "ah_I"
        },
        {
          "duration": 0.1,
          "phone": "t_E"
        }
      ],
      "start": 0.58,
      "startOffset": 0,
      "word": "But"
    },
    {
      "alignedWord": "he",
      "case": "success",
      "end": 1.83,
      "endOffset": 6,
      "phones": [
        {
          "duration": 0.17,
          "phone": "hh_B"
        },
        {
          "duration": 0.09,
          "phone": "iy_E"
        }
      ],
      "start": 1.57,
      "startOffset": 4,
      "word": "he"
    },
    {
      "alignedWord": "no",
      "case": "success",
      "end": 2.0100000000000002,
      "endOffset": 9,
      "phones": [
        {
          "duration": 0.07,
          "phone": "n_B"
        },
        {
          "duration": 0.11,
          "phone": "ow_E"
        }
      ],
      "start": 1.83,
      "startOffset": 7,
      "word": "no"
    },
    {
      "alignedWord": "longer",
      "case": "success",
      "end": 2.36,
      "endOffset": 16,
      "phones": [
        {
          "duration": 0.07,
          "phone": "l_B"
        },
        {
          "duration": 0.08,
          "phone": "ao_I"
        },
        {
          "duration": 0.05,
          "phone": "ng_I"
        },
        {
          "duration": 0.07,
          "phone": "g_I"
        },
        {
          "duration": 0.08,
          "phone": "er_E"
        }
      ],
      "start": 2.01,
      "startOffset": 10,
      "word": "longer"
    },
    {
      "alignedWord": "cared",
      "case": "success",
      "end": 2.76,
      "endOffset": 22,
      "phones": [
        {
          "duration": 0.13,
          "phone": "k_B"
        },
        {
          "duration": 0.13,
          "phone": "eh_I"
        },
        {
          "duration": 0.08,
          "phone": "r_I"
        },
        {
          "duration": 0.06,
          "phone": "d_E"
        }
      ],
      "start": 2.36,
      "startOffset": 17,
      "word": "cared"
    },
    {
      "alignedWord": "quite",
      "case": "success",
      "end": 3.05,
      "endOffset": 28,
      "phones": [
        {
          "duration": 0.09,
          "phone": "k_B"
        },
        {
          "duration": 0.04,
          "phone": "w_I"
        },
        {
          "duration": 0.06,
          "phone": "ay_I"
        },
        {
          "duration": 0.09,
          "phone": "t_E"
        }
      ],
      "start": 2.77,
      "startOffset": 23,
      "word": "quite"
    },
    {
      "alignedWord": "so",
      "case": "success",
      "end": 3.25,
      "endOffset": 31,
      "phones": [
        {
          "duration": 0.11,
          "phone": "s_B"
        },
        {
          "duration": 0.09,
          "phone": "ow_E"
        }
      ],
      "start": 3.05,
      "startOffset": 29,
      "word": "so"
    },
    {
      "alignedWord": "much",
      "case": "success",
      "end": 3.7,
      "endOffset": 36,
      "phones": [
        {
          "duration": 0.11,
          "phone": "m_B"
        },
        {
          "duration": 0.09,
          "phone": "ah_I"
        },
        {
          "duration": 0.25,
          "phone": "ch_E"
        }
      ],
      "start": 3.25,
      "startOffset": 32,
      "word": "much"
    },
    {
      "alignedWord": "for",
      "case": "success",
      "end": 4.279999999999999,
      "endOffset": 40,
      "phones": [
        {
          "duration": 0.06,
          "phone": "f_B"
        },
        {
          "duration": 0.08,
          "phone": "er_E"
        }
      ],
      "start": 4.14,
      "startOffset": 37,
      "word": "for"
    },
    {
      "alignedWord": "that",
      "case": "success",
      "end": 4.55,
      "endOffset": 45,
      "phones": [
        {
          "duration": 0.09,
          "phone": "dh_B"
        },
        {
          "duration": 0.07,
          "phone": "ae_I"
        },
        {
          "duration": 0.1,
          "phone": "t_E"
        }
      ],
      "start": 4.29,
      "startOffset": 41,
      "word": "that"
    },
    {
      "alignedWord": "form",
      "case": "success",
      "end": 4.7299999999999995,
      "endOffset": 50,
      "phones": [
        {
          "duration": 0.09,
          "phone": "f_B"
        },
        {
          "duration": 0.07,
          "phone": "ao_I"
        },
        {
          "duration": 0.01,
          "phone": "r_I"
        },
        {
          "duration": 0.01,
          "phone": "m_E"
        }
      ],
      "start": 4.55,
      "startOffset": 46,
      "word": "form"
    },
    {
      "alignedWord": "of",
      "case": "success",
      "end": 4.97,
      "endOffset": 53,
      "phones": [
        {
          "duration": 0.15,
          "phone": "ah_B"
        },
        {
          "duration": 0.07,
          "phone": "v_E"
        }
      ],
      "start": 4.75,
      "startOffset": 51,
      "word": "of"
    },
    {
      "alignedWord": "diversion",
      "case": "success",
      "end": 5.74,
      "endOffset": 63,
      "phones": [
        {
          "duration": 0.08,
          "phone": "d_B"
        },
        {
          "duration": 0.14,
          "phone": "ay_I"
        },
        {
          "duration": 0.11,
          "phone": "v_I"
        },
        {
          "duration": 0.11,
          "phone": "er_I"
        },
        {
          "duration": 0.12,
          "phone": "zh_I"
        },
        {
          "duration": 0.09,
          "phone": "ah_I"
        },
        {
          "duration": 0.12,
          "phone": "n_E"
        }
      ],
      "start": 4.97,
      "startOffset": 54,
      "word": "diversion"
    }
  ]
}