{"transcript": "the motives for a transient amendment were becoming paralyzed, and the effect had ceased with the cause.\"", "words": [{"alignedWord": "the", "case": "success", "end": 0.02, "endOffset": 3, "phones": [{"duration": 0.01, "phone": "dh_B"}, {"duration": 0.01, "phone": "ah_E"}], "start": 0.0, "startOffset": 0, "word": "the"}, {"alignedWord": "motives", "case": "success", "end": 0.6299999999999999, "endOffset": 11, "phones": [{"duration": 0.14, "phone": "m_B"}, {"duration": 0.11, "phone": "ow_I"}, {"duration": 0.08, "phone": "t_I"}, {"duration": 0.08, "phone": "ih_I"}, {"duration": 0.05, "phone": "v_I"}, {"duration": 0.11, "phone": "z_E"}], "start": 0.06, "startOffset": 4, "word": "motives"}, {"alignedWord": "for", "case": "success", "end": 0.81, "endOffset": 15, "phones": [{"duration": 0.1, "phone": "f_B"}, {"duration": 0.07, "phone": "er_E"}], "start": 0.64, "startOffset": 12, "word": "for"}, {"alignedWord": "a", "case": "success", "end": 0.8700000000000001, "endOffset": 17, "phones": [{"duration": 0.06, "phone": "ah_S"}], "start": 0.81, "startOffset": 16, "word": "a"}, {"alignedWord": "transient", "case": "success", "end": 1.49, "endOffset": 27, "phones": [{"duration": 0.1, "phone": "t_B"}, {"duration": 0.1, "phone": "r_I"}, {"duration": 0.11, "phone": "ae_I"}, {"duration": 0.06, "phone": "n_I"}, {"duration": 0.09, "phone": "zh_I"}, {"duration": 0.09, "phone": "ah_I"}, {"duration": 0.02, "phone": "n_I"}, {"duration": 0.05, "phone": "t_E"}], "start": 0.87, "startOffset": 18, "word": "transient"}, {"alignedWord": "amendment", "case": "success", "end": 2.1, "endOffset": 37, "phones": [{"duration": 0.07, "phone": "ah_B"}, {"duration": 0.09, "phone": "m_I"}, {"duration": 0.11, "phone": "eh_I"}, {"duration": 0.06, "phone": "n_I"}, {"duration": 0.05, "phone": "d_I"}, {"duration": 0.06, "phone": "m_I"}, {"duration": 0.04, "phone": "ah_I"}, {"duration": 0.04, "phone": "n_I"}, {"duration": 0.07, "phone": "t_E"}], "start": 1.51, "startOffset": 28, "word": "amendment"}, {"alignedWord": "were", "case": "success", "end": 2.26, "endOffset": 42, "phones": [{"duration": 0.11, "phone": "w_B"}, {"duration": 0.04, "phone": "er_E"}], "start": 2.11, "startOffset": 38, "word": "were"}, {"alignedWord": "becoming", "case": "success", "end": 2.7199999999999998, "endOffset": 51, "phones": [{"duration": 0.04, "phone": "b_B"}, {"duration": 0.06, "phone": "ih_I"}, {"duration": 0.1, "phone": "k_I"}, {"duration": 0.07, "phone": "ah_I"}, {"duration": 0.05, "phone": "m_I"}, {"duration": 0.06, "phone": "ih_I"}, {"duration": 0.08, "phone": "ng_E"}], "start": 2.26, "startOffset": 43, "word": "becoming"}, {"alignedWord": "paralyzed", "case": "success", "end": 3.6, "endOffset": 61, "phones": [{"duration": 0.09, "phone": "p_B"}, {"duration": 0.06, "phone": "eh_I"}, {"duration": 0.08, "phone": "r_I"}, {"duration": 0.08, "phone": "ah_I"}, {"duration": 0.12, "phone": "l_I"}, {"duration": 0.2, "phone": "ay_I"}, {"duration": 0.11, "phone": "z_I"}, {"duration": 0.14, "phone": "d_E"}], "start": 2.72, "startOffset": 52, "word": "paralyzed"}, {"alignedWord": "and", "case": "success", "end": 4.01, "endOffset": 66, "phones": [{"duration": 0.09, "phone": "ae_B"}, {"duration": 0.05, "phone": "n_I"}, {"duration": 0.04, "phone": "d_E"}], "start": 3.83, "startOffset": 63, "word": "and"}, {"alignedWord": "the", "case": "success", "end": 4.14, "endOffset": 70, "phones": [{"duration": 0.05, "phone": "dh_B"}, {"duration": 0.08, "phone": "iy_E"}], "start": 4.01, "startOffset": 67, "word": "the"}, {"alignedWord": "effect", "case": "success", "end": 4.609999999999999, "endOffset": 77, "phones": [{"duration": 0.07, "phone": "ah_B"}, {"duration": 0.15, "phone": "f_I"}, {"duration": 0.11, "phone": "eh_I"}, {"duration": 0.06, "phone": "k_I"}, {"duration": 0.08, "phone": "t_E"}], "start": 4.14, "startOffset": 71, "word": "effect"}, {"alignedWord": "had", "case": "success", "end": 4.83, "endOffset": 81, "phones": [{"duration": 0.06, "phone": "hh_B"}, {"duration": 0.07, "phone": "ae_I"}, {"duration": 0.09, "phone": "d_E"}], "start": 4.61, "startOffset": 78, "word": "had"}, {"alignedWord": "ceased", "case": "success", "end": 5.3500000000000005, "endOffset": 88, "phones": [{"duration": 0.15, "phone": "s_B"}, {"duration": 0.14, "phone": "iy_I"}, {"duration": 0.08, "phone": "s_I"}, {"duration": 0.12, "phone": "t_E"}], "start": 4.86, "startOffset": 82, "word": "ceased"}, {"alignedWord": "with", "case": "success", "end": 5.61, "endOffset": 93, "phones": [{"duration": 0.08, "phone": "w_B"}, {"duration": 0.05, "phone": "ih_I"}, {"duration": 0.08, "phone": "th_E"}], "start": 5.4, "startOffset": 89, "word": "with"}, {"alignedWord": "the", "case": "success", "end": 5.74, "endOffset": 97, "phones": [{"duration": 0.05, "phone": "dh_B"}, {"duration": 0.06, "phone": "ah_E"}], "start": 5.63, "startOffset": 94, "word": "the"}, {"alignedWord": "cause", "case": "success", "end": 6.36, "endOffset": 103, "phones": [{"duration": 0.12, "phone": "k_B"}, {"duration": 0.25, "phone": "ao_I"}, {"duration": 0.25, "phone": "z_E"}], "start": 5.74, "startOffset": 98, "word": "cause"}]}