{"transcript": "It was intended as far as possible that, except awaiting trial, no prisoner should find himself relegated to Newgate.", "words": [{"alignedWord": "it", "case": "success", "end": 0.14, "endOffset": 2, "phones": [{"duration": 0.06, "phone": "ih_B"}, {"duration": 0.08, "phone": "t_E"}], "start": 0.0, "startOffset": 0, "word": "It"}, {"alignedWord": "was", "case": "success", "end": 0.28, "endOffset": 6, "phones": [{"duration": 0.03, "phone": "w_B"}, {"duration": 0.07, "phone": "ah_I"}, {"duration": 0.04, "phone": "z_E"}], "start": 0.14, "startOffset": 3, "word": "was"}, {"alignedWord": "intended", "case": "success", "end": 0.86, "endOffset": 15, "phones": [{"duration": 0.06, "phone": "ih_B"}, {"duration": 0.06, "phone": "n_I"}, {"duration": 0.11, "phone": "t_I"}, {"duration": 0.08, "phone": "eh_I"}, {"duration": 0.07, "phone": "n_I"}, {"duration": 0.06, "phone": "d_I"}, {"duration": 0.08, "phone": "ah_I"}, {"duration": 0.06, "phone": "d_E"}], "start": 0.28, "startOffset": 7, "word": "intended"}, {"alignedWord": "as", "case": "success", "end": 1.0, "endOffset": 18, "phones": [{"duration": 0.07, "phone": "eh_B"}, {"duration": 0.07, "phone": "z_E"}], "start": 0.86, "startOffset": 16, "word": "as"}, {"alignedWord": "far", "case": "success", "end": 1.25, "endOffset": 22, "phones": [{"duration": 0.1, "phone": "f_B"}, {"duration": 0.08, "phone": "aa_I"}, {"duration": 0.07, "phone": "r_E"}], "start": 1.0, "startOffset": 19, "word": "far"}, {"alignedWord": "as", "case": "success", "end": 1.37, "endOffset": 25, "phones": [{"duration": 0.06, "phone": "eh_B"}, {"duration": 0.06, "phone": "z_E"}], "start": 1.25, "startOffset": 23, "word": "as"}, {"alignedWord": "possible", "case": "success", "end": 1.9500000000000002, "endOffset": 34, "phones": [{"duration": 0.09, "phone": "p_B"}, {"duration": 0.17, "phone": "aa_I"}, {"duration": 0.06, "phone": "s_I"}, {"duration": 0.07, "phone": "ah_I"}, {"duration": 0.04, "phone": "b_I"}, {"duration": 0.06, "phone": "ah_I"}, {"duration": 0.09, "phone": "l_E"}], "start": 1.37, "startOffset": 26, "word": "possible"}, {"alignedWord": "that", "case": "success", "end": 2.32, "endOffset": 39, "phones": [{"duration": 0.07, "phone": "dh_B"}, {"duration": 0.09, "phone": "ae_I"}, {"duration": 0.21, "phone": "t_E"}], "start": 1.95, "startOffset": 35, "word": "that"}, {"alignedWord": "except", "case": "success", "end": 2.95, "endOffset": 47, "phones": [{"duration": 0.07, "phone": "ih_B"}, {"duration": 0.1, "phone": "k_I"}, {"duration": 0.1, "phone": "s_I"}, {"duration": 0.07, "phone": "eh_I"}, {"duration": 0.07, "phone": "p_I"}, {"duration": 0.08, "phone": "t_E"}], "start": 2.46, "startOffset": 41, "word": "except"}, {"alignedWord": "awaiting", "case": "success", "end": 3.45, "endOffset": 56, "phones": [{"duration": 0.08, "phone": "ah_B"}, {"duration": 0.12, "phone": "w_I"}, {"duration": 0.05, "phone": "ey_I"}, {"duration": 0.08, "phone": "t_I"}, {"duration": 0.05, "phone": "ih_I"}, {"duration": 0.1, "phone": "ng_E"}], "start": 2.97, "startOffset": 48, "word": "awaiting"}, {"alignedWord": "trial", "case": "success", "end": 4.09, "endOffset": 62, "phones": [{"duration": 0.1, "phone": "t_B"}, {"duration": 0.11, "phone": "r_I"}, {"duration": 0.22, "phone": "ay_I"}, {"duration": 0.21, "phone": "l_E"}], "start": 3.45, "startOffset": 57, "word": "trial"}, {"alignedWord": "no", "case": "success", "end": 4.69, "endOffset": 66, "phones": [{"duration": 0.12, "phone": "n_B"}, {"duration": 0.13, "phone": "ow_E"}], "start": 4.44, "startOffset": 64, "word": "no"}, {"alignedWord": "prisoner", "case": "success", "end": 5.2, "endOffset": 75, "phones": [{"duration": 0.1, "phone": "p_B"}, {"duration": 0.05, "phone": "r_I"}, {"duration": 0.1, "phone": "ih_I"}, {"duration": 0.03, "phone": "z_I"}, {"duration": 0.06, "phone": "ah_I"}, {"duration": 0.07, "phone": "n_I"}, {"duration": 0.1, "phone": "er_E"}], "start": 4.69, "startOffset": 67, "word": "prisoner"}, {"alignedWord": "should", "case": "success", "end": 5.4399999999999995, "endOffset": 82, "phones": [{"duration": 0.1, "phone": "sh_B"}, {"duration": 0.05, "phone": "uh_I"}, {"duration": 0.07, "phone": "d_E"}], "start": 5.22, "startOffset": 76, "word": "should"}, {"alignedWord": "find", "case": "success", "end": 5.75, "endOffset": 87, "phones": [{"duration": 0.1, "phone": "f_B"}, {"duration": 0.11, "phone": "ay_I"}, {"duration": 0.04, "phone": "n_I"}, {"duration": 0.06, "phone": "d_E"}], "start": 5.44, "startOffset": 83, "word": "find"}, {"alignedWord": "himself", "case": "success", "end": 6.19, "endOffset": 95, "phones": [{"duration": 0.02, "phone": "hh_B"}, {"duration": 0.06, "phone": "ih_I"}, {"duration": 0.08, "phone": "m_I"}, {"duration": 0.08, "phone": "s_I"}, {"duration": 0.08, "phone": "eh_I"}, {"duration": 0.06, "phone": "l_I"}, {"duration": 0.06, "phone": "f_E"}], "start": 5.75, "startOffset": 88, "word": "himself"}, {"alignedWord": "relegated", "case": "success", "end": 6.9, "endOffset": 105, "phones": [{"duration": 0.08, "phone": "r_B"}, {"duration": 0.06, "phone": "eh_I"}, {"duration": 0.07, "phone": "l_I"}, {"duration": 0.08, "phone": "ah_I"}, {"duration": 0.08, "phone": "g_I"}, {"duration": 0.12, "phone": "ey_I"}, {"duration": 0.05, "phone": "t_I"}, {"duration": 0.08, "phone": "ih_I"}, {"duration": 0.08, "phone": "d_E"}], "start": 6.2, "startOffset": 96, "word": "relegated"}, {"alignedWord": "to", "case": "success", "end": 7.1000000000000005, "endOffset": 108, "phones": [{"duration": 0.08, "phone": "t_B"}, {"duration": 0.08, "phone": "ih_E"}], "start": 6.94, "startOffset": 106, "word": "to"}, {"alignedWord": "<unk>", "case": "success", "end": 7.6000000000000005, "endOffset": 116, "phones": [{"duration": 0.49, "phone": "oov_S"}], "start": 7.11, "startOffset": 109, "word": "Newgate"}]}