{"transcript": "the situation having been proved by long experience to be salubrious.", "words": [{"alignedWord": "the", "case": "success", "end": 0.15, "endOffset": 3, "phones": [{"duration": 0.07, "phone": "dh_B"}, {"duration": 0.08, "phone": "ah_E"}], "start": 0.0, "startOffset": 0, "word": "the"}, {"alignedWord": "situation", "case": "success", "end": 0.91, "endOffset": 13, "phones": [{"duration": 0.1, "phone": "s_B"}, {"duration": 0.07, "phone": "ih_I"}, {"duration": 0.12, "phone": "ch_I"}, {"duration": 0.13, "phone": "uw_I"}, {"duration": 0.12, "phone": "ey_I"}, {"duration": 0.11, "phone": "sh_I"}, {"duration": 0.06, "phone": "ah_I"}, {"duration": 0.05, "phone": "n_E"}], "start": 0.15, "startOffset": 4, "word": "situation"}, {"alignedWord": "having", "case": "success", "end": 1.27, "endOffset": 20, "phones": [{"duration": 0.09, "phone": "hh_B"}, {"duration": 0.08, "phone": "ae_I"}, {"duration": 0.04, "phone": "v_I"}, {"duration": 0.06, "phone": "ih_I"}, {"duration": 0.08, "phone": "ng_E"}], "start": 0.92, "startOffset": 14, "word": "having"}, {"alignedWord": "been", "case": "success", "end": 1.45, "endOffset": 25, "phones": [{"duration": 0.04, "phone": "b_B"}, {"duration": 0.08, "phone": "ih_I"}, {"duration": 0.06, "phone": "n_E"}], "start": 1.27, "startOffset": 21, "word": "been"}, {"alignedWord": "proved", "case": "success", "end": 1.83, "endOffset": 32, "phones": [{"duration": 0.06, "phone": "p_B"}, {"duration": 0.1, "phone": "r_I"}, {"duration": 0.16, "phone": "uw_I"}, {"duration": 0.03, "phone": "v_I"}, {"duration": 0.03, "phone": "d_E"}], "start": 1.45, "startOffset": 26, "word": "proved"}, {"alignedWord": "by", "case": "success", "end": 2.0500000000000003, "endOffset": 35, "phones": [{"duration": 0.11, "phone": "b_B"}, {"duration": 0.1, "phone": "ay_E"}], "start": 1.84, "startOffset": 33, "word": "by"}, {"alignedWord": "long", "case": "success", "end": 2.3699999999999997, "endOffset": 40, "phones": [{"duration": 0.11, "phone": "l_B"}, {"duration": 0.12, "phone": "ao_I"}, {"duration": 0.09, "phone": "ng_E"}], "start": 2.05, "startOffset": 36, "word": "long"}, {"alignedWord": "experience", "case": "success", "end": 3.1500000000000004, "endOffset": 51, "phones": [{"duration": 0.07, "phone": "ih_B"}, {"duration": 0.08, "phone": "k_I"}, {"duration": 0.08, "phone": "s_I"}, {"duration": 0.06, "phone": "p_I"}, {"duration": 0.08, "phone": "ih_I"}, {"duration": 0.08, "phone": "r_I"}, {"duration": 0.11, "phone": "iy_I"}, {"duration": 0.07, "phone": "ah_I"}, {"duration": 0.07, "phone": "n_I"}, {"duration": 0.08, "phone": "s_E"}], "start": 2.37, "startOffset": 41, "word": "experience"}, {"alignedWord": "to", "case": "success", "end": 3.62, "endOffset": 54, "phones": [{"duration": 0.08, "phone": "t_B"}, {"duration": 0.05, "phone": "ih_E"}], "start": 3.49, "startOffset": 52, "word": "to"}, {"alignedWord": "be", "case": "success", "end": 3.8200000000000003, "endOffset": 57, "phones": [{"duration": 0.08, "phone": "b_B"}, {"duration": 0.12, "phone": "iy_E"}], "start": 3.62, "startOffset": 55, "word": "be"}, {"alignedWord": "<unk>", "case": "success", "end": 4.6499999999999995, "endOffset": 68, "phones": [{"duration": 0.83, "phone": "oov_S"}], "start": 3.82, "startOffset": 58, "word": "salubrious"}]}