{"transcript": "Fat and carbohydrate foods, then, never become living matter.", "words": [{"alignedWord": "fat", "case": "success", "end": 0.41, "endOffset": 3, "phones": [{"duration": 0.12, "phone": "f_B"}, {"duration": 0.15, "phone": "ae_I"}, {"duration": 0.14, "phone": "t_E"}], "start": 0.0, "startOffset": 0, "word": "Fat"}, {"alignedWord": "and", "case": "success", "end": 0.62, "endOffset": 7, "phones": [{"duration": 0.06, "phone": "ah_B"}, {"duration": 0.06, "phone": "n_I"}, {"duration": 0.08, "phone": "d_E"}], "start": 0.42, "startOffset": 4, "word": "and"}, {"alignedWord": "carbohydrate", "case": "success", "end": 1.42, "endOffset": 20, "phones": [{"duration": 0.07, "phone": "k_B"}, {"duration": 0.07, "phone": "aa_I"}, {"duration": 0.05, "phone": "r_I"}, {"duration": 0.06, "phone": "b_I"}, {"duration": 0.08, "phone": "ow_I"}, {"duration": 0.1, "phone": "hh_I"}, {"duration": 0.09, "phone": "ay_I"}, {"duration": 0.08, "phone": "d_I"}, {"duration": 0.06, "phone": "r_I"}, {"duration": 0.05, "phone": "ey_I"}, {"duration": 0.09, "phone": "t_E"}], "start": 0.62, "startOffset": 8, "word": "carbohydrate"}, {"alignedWord": "foods", "case": "success", "end": 1.98, "endOffset": 26, "phones": [{"duration": 0.14, "phone": "f_B"}, {"duration": 0.24, "phone": "uw_I"}, {"duration": 0.07, "phone": "d_I"}, {"duration": 0.11, "phone": "z_E"}], "start": 1.42, "startOffset": 21, "word": "foods"}, {"alignedWord": "then", "case": "success", "end": 2.4, "endOffset": 32, "phones": [{"duration": 0.09, "phone": "dh_B"}, {"duration": 0.11, "phone": "eh_I"}, {"duration": 0.19, "phone": "n_E"}], "start": 2.01, "startOffset": 28, "word": "then"}, {"alignedWord": "never", "case": "success", "end": 3.0, "endOffset": 39, "phones": [{"duration": 0.13, "phone": "n_B"}, {"duration": 0.1, "phone": "eh_I"}, {"duration": 0.08, "phone": "v_I"}, {"duration": 0.14, "phone": "er_E"}], "start": 2.55, "startOffset": 34, "word": "never"}, {"alignedWord": "become", "case": "success", "end": 3.44, "endOffset": 46, "phones": [{"duration": 0.05, "phone": "b_B"}, {"duration": 0.07, "phone": "ih_I"}, {"duration": 0.1, "phone": "k_I"}, {"duration": 0.1, "phone": "ah_I"}, {"duration": 0.11, "phone": "m_E"}], "start": 3.01, "startOffset": 40, "word": "become"}, {"alignedWord": "living", "case": "success", "end": 3.8, "endOffset": 53, "phones": [{"duration": 0.09, "phone": "l_B"}, {"duration": 0.06, "phone": "ih_I"}, {"duration": 0.04, "phone": "v_I"}, {"duration": 0.09, "phone": "ih_I"}, {"duration": 0.08, "phone": "ng_E"}], "start": 3.44, "startOffset": 47, "word": "living"}, {"alignedWord": "matter", "case": "success", "end": 4.3100000000000005, "endOffset": 60, "phones": [{"duration": 0.11, "phone": "m_B"}, {"duration": 0.11, "phone": "ae_I"}, {"duration": 0.08, "phone": "t_I"}, {"duration": 0.2, "phone": "er_E"}], "start": 3.81, "startOffset": 54, "word": "matter"}]}