{"transcript": "When Oswald was arrested in the Texas Theatre, he was wearing a brown sport shirt with a hole in the right sleeve at the elbow.", "words": [{"alignedWord": "when", "case": "success", "end": 0.17, "endOffset": 4, "phones": [{"duration": 0.01, "phone": "w_B"}, {"duration": 0.01, "phone": "eh_I"}, {"duration": 0.01, "phone": "n_E"}], "start": 0.14, "startOffset": 0, "word": "When"}, {"alignedWord": "oswald", "case": "success", "end": 0.76, "endOffset": 11, "phones": [{"duration": 0.21, "phone": "ao_B"}, {"duration": 0.1, "phone": "z_I"}, {"duration": 0.05, "phone": "w_I"}, {"duration": 0.08, "phone": "ao_I"}, {"duration": 0.06, "phone": "l_I"}, {"duration": 0.08, "phone": "d_E"}], "start": 0.18, "startOffset": 5, "word": "Oswald"}, {"alignedWord": "was", "case": "success", "end": 0.95, "endOffset": 15, "phones": [{"duration": 0.04, "phone": "w_B"}, {"duration": 0.06, "phone": "ah_I"}, {"duration": 0.09, "phone": "z_E"}], "start": 0.76, "startOffset": 12, "word": "was"}, {"alignedWord": "arrested", "case": "success", "end": 1.54, "endOffset": 24, "phones": [{"duration": 0.12, "phone": "er_B"}, {"duration": 0.11, "phone": "eh_I"}, {"duration": 0.09, "phone": "s_I"}, {"duration": 0.07, "phone": "t_I"}, {"duration": 0.11, "phone": "ih_I"}, {"duration": 0.09, "phone": "d_E"}], "start": 0.95, "startOffset": 16, "word": "arrested"}, {"alignedWord": "in", "case": "success", "end": 1.7, "endOffset": 27, "phones": [{"duration": 0.09, "phone": "ih_B"}, {"duration": 0.06, "phone": "n_E"}], "start": 1.55, "startOffset": 25, "word": "in"}, {"alignedWord": "the", "case": "success", "end": 1.8, "endOffset": 31, "phones": [{"duration": 0.03, "phone": "dh_B"}, {"duration": 0.07, "phone": "ah_E"}], "start": 1.7, "startOffset": 28, "word": "the"}, {"alignedWord": "texas", "case": "success", "end": 2.2800000000000002, "endOffset": 37, "phones": [{"duration": 0.06, "phone": "t_B"}, {"duration": 0.08, "phone": "eh_I"}, {"duration": 0.06, "phone": "k_I"}, {"duration": 0.07, "phone": "s_I"}, {"duration": 0.09, "phone": "ah_I"}, {"duration": 0.1, "phone": "s_E"}], "start": 1.82, "startOffset": 32, "word": "Texas"}, {"alignedWord": "theatre", "case": "success", "end": 2.8099999999999996, "endOffset": 45, "phones": [{"duration": 0.1, "phone": "th_B"}, {"duration": 0.11, "phone": "iy_I"}, {"duration": 0.03, "phone": "ah_I"}, {"duration": 0.06, "phone": "t_I"}, {"duration": 0.23, "phone": "er_E"}], "start": 2.28, "startOffset": 38, "word": "Theatre"}, {"alignedWord": "he", "case": "success", "end": 3.46, "endOffset": 49, "phones": [{"duration": 0.2, "phone": "hh_B"}, {"duration": 0.08, "phone": "iy_E"}], "start": 3.18, "startOffset": 47, "word": "he"}, {"alignedWord": "was", "case": "success", "end": 3.66, "endOffset": 53, "phones": [{"duration": 0.05, "phone": "w_B"}, {"duration": 0.07, "phone": "ah_I"}, {"duration": 0.08, "phone": "z_E"}], "start": 3.46, "startOffset": 50, "word": "was"}, {"alignedWord": "wearing", "case": "success", "end": 4.04, "endOffset": 61, "phones": [{"duration": 0.07, "phone": "w_B"}, {"duration": 0.07, "phone": "eh_I"}, {"duration": 0.09, "phone": "r_I"}, {"duration": 0.07, "phone": "ih_I"}, {"duration": 0.08, "phone": "ng_E"}], "start": 3.66, "startOffset": 54, "word": "wearing"}, {"alignedWord": "a", "case": "success", "end": 4.11, "endOffset": 63, "phones": [{"duration": 0.07, "phone": "ah_S"}], "start": 4.04, "startOffset": 62, "word": "a"}, {"alignedWord": "brown", "case": "success", "end": 4.55, "endOffset": 69, "phones": [{"duration": 0.1, "phone": "b_B"}, {"duration": 0.06, "phone": "r_I"}, {"duration": 0.14, "phone": "aw_I"}, {"duration": 0.13, "phone": "n_E"}], "start": 4.12, "startOffset": 64, "word": "brown"}, {"alignedWord": "sport", "case": "success", "end": 4.92, "endOffset": 75, "phones": [{"duration": 0.06, "phone": "s_B"}, {"duration": 0.09, "phone": "p_I"}, {"duration": 0.07, "phone": "ao_I"}, {"duration": 0.06, "phone": "r_I"}, {"duration": 0.08, "phone": "t_E"}], "start": 4.56, "startOffset": 70, "word": "sport"}, {"alignedWord": "shirt", "case": "success", "end": 5.22, "endOffset": 81, "phones": [{"duration": 0.13, "phone": "sh_B"}, {"duration": 0.1, "phone": "er_I"}, {"duration": 0.07, "phone": "t_E"}], "start": 4.92, "startOffset": 76, "word": "shirt"}, {"alignedWord": "with", "case": "success", "end": 5.46, "endOffset": 86, "phones": [{"duration": 0.07, "phone": "w_B"}, {"duration": 0.03, "phone": "ih_I"}, {"duration": 0.06, "phone": "th_E"}], "start": 5.3, "startOffset": 82, "word": "with"}, {"alignedWord": "a", "case": "success", "end": 5.52, "endOffset": 88, "phones": [{"duration": 0.06, "phone": "ah_S"}], "start": 5.46, "startOffset": 87, "word": "a"}, {"alignedWord": "hole", "case": "success", "end": 5.92, "endOffset": 93, "phones": [{"duration": 0.12, "phone": "hh_B"}, {"duration": 0.16, "phone": "ow_I"}, {"duration": 0.12, "phone": "l_E"}], "start": 5.52, "startOffset": 89, "word": "hole"}, {"alignedWord": "in", "case": "success", "end": 6.0600000000000005, "endOffset": 96, "phones": [{"duration": 0.07, "phone": "ih_B"}, {"duration": 0.05, "phone": "n_E"}], "start": 5.94, "startOffset": 94, "word": "in"}, {"alignedWord": "the", "case": "success", "end": 6.17, "endOffset": 100, "phones": [{"duration": 0.04, "phone": "dh_B"}, {"duration": 0.07, "phone": "ah_E"}], "start": 6.06, "startOffset": 97, "word": "the"}, {"alignedWord": "right", "case": "success", "end": 6.47, "endOffset": 106, "phones": [{"duration": 0.1, "phone": "r_B"}, {"duration": 0.1, "phone": "ay_I"}, {"duration": 0.1, "phone": "t_E"}], "start": 6.17, "startOffset": 101, "word": "right"}, {"alignedWord": "sleeve", "case": "success", "end": 6.87, "endOffset": 113, "phones": [{"duration": 0.12, "phone": "s_B"}, {"duration": 0.09, "phone": "l_I"}, {"duration": 0.12, "phone": "iy_I"}, {"duration": 0.07, "phone": "v_E"}], "start": 6.47, "startOffset": 107, "word": "sleeve"}, {"alignedWord": "at", "case": "success", "end": 7.11, "endOffset": 116, "phones": [{"duration": 0.12, "phone": "ae_B"}, {"duration": 0.07, "phone": "t_E"}], "start": 6.92, "startOffset": 114, "word": "at"}, {"alignedWord": "the", "case": "success", "end": 7.260000000000001, "endOffset": 120, "phones": [{"duration": 0.05, "phone": "dh_B"}, {"duration": 0.1, "phone": "iy_E"}], "start": 7.11, "startOffset": 117, "word": "the"}, {"alignedWord": "elbow", "case": "success", "end": 7.7299999999999995, "endOffset": 126, "phones": [{"duration": 0.11, "phone": "eh_B"}, {"duration": 0.08, "phone": "l_I"}, {"duration": 0.1, "phone": "b_I"}, {"duration": 0.18, "phone": "ow_E"}], "start": 7.26, "startOffset": 121, "word": "elbow"}]}