{"transcript": "The Commission is satisfied that the lineups were conducted fairly.", "words": [{"alignedWord": "the", "case": "success", "end": 0.1, "endOffset": 3, "phones": [{"duration": 0.03, "phone": "dh_B"}, {"duration": 0.07, "phone": "ah_E"}], "start": 0.0, "startOffset": 0, "word": "The"}, {"alignedWord": "commission", "case": "success", "end": 0.54, "endOffset": 14, "phones": [{"duration": 0.06, "phone": "k_B"}, {"duration": 0.07, "phone": "ah_I"}, {"duration": 0.05, "phone": "m_I"}, {"duration": 0.06, "phone": "ih_I"}, {"duration": 0.08, "phone": "sh_I"}, {"duration": 0.05, "phone": "ah_I"}, {"duration": 0.07, "phone": "n_E"}], "start": 0.1, "startOffset": 4, "word": "Commission"}, {"alignedWord": "is", "case": "success", "end": 0.7000000000000001, "endOffset": 17, "phones": [{"duration": 0.1, "phone": "ih_B"}, {"duration": 0.05, "phone": "z_E"}], "start": 0.55, "startOffset": 15, "word": "is"}, {"alignedWord": "satisfied", "case": "success", "end": 1.48, "endOffset": 27, "phones": [{"duration": 0.12, "phone": "s_B"}, {"duration": 0.11, "phone": "ae_I"}, {"duration": 0.06, "phone": "t_I"}, {"duration": 0.06, "phone": "ah_I"}, {"duration": 0.08, "phone": "s_I"}, {"duration": 0.1, "phone": "f_I"}, {"duration": 0.15, "phone": "ay_I"}, {"duration": 0.1, "phone": "d_E"}], "start": 0.7, "startOffset": 18, "word": "satisfied"}, {"alignedWord": "that", "case": "success", "end": 1.8299999999999998, "endOffset": 32, "phones": [{"duration": 0.08, "phone": "dh_B"}, {"duration": 0.03, "phone": "ae_I"}, {"duration": 0.06, "phone": "t_E"}], "start": 1.66, "startOffset": 28, "word": "that"}, {"alignedWord": "the", "case": "success", "end": 1.9500000000000002, "endOffset": 36, "phones": [{"duration": 0.05, "phone": "dh_B"}, {"duration": 0.07, "phone": "ah_E"}], "start": 1.83, "startOffset": 33, "word": "the"}, {"alignedWord": "lineups", "case": "success", "end": 2.45, "endOffset": 44, "phones": [{"duration": 0.11, "phone": "l_B"}, {"duration": 0.13, "phone": "ay_I"}, {"duration": 0.06, "phone": "n_I"}, {"duration": 0.05, "phone": "ah_I"}, {"duration": 0.08, "phone": "p_I"}, {"duration": 0.07, "phone": "s_E"}], "start": 1.95, "startOffset": 37, "word": "lineups"}, {"alignedWord": "were", "case": "success", "end": 2.6100000000000003, "endOffset": 49, "phones": [{"duration": 0.08, "phone": "w_B"}, {"duration": 0.08, "phone": "er_E"}], "start": 2.45, "startOffset": 45, "word": "were"}, {"alignedWord": "conducted", "case": "success", "end": 3.23, "endOffset": 59, "phones": [{"duration": 0.05, "phone": "k_B"}, {"duration": 0.06, "phone": "ah_I"}, {"duration": 0.05, "phone": "n_I"}, {"duration": 0.06, "phone": "d_I"}, {"duration": 0.08, "phone": "ah_I"}, {"duration": 0.09, "phone": "k_I"}, {"duration": 0.05, "phone": "t_I"}, {"duration": 0.08, "phone": "ah_I"}, {"duration": 0.08, "phone": "d_E"}], "start": 2.63, "startOffset": 50, "word": "conducted"}, {"alignedWord": "fairly", "case": "success", "end": 3.7800000000000002, "endOffset": 66, "phones": [{"duration": 0.1, "phone": "f_B"}, {"duration": 0.12, "phone": "eh_I"}, {"duration": 0.08, "phone": "r_I"}, {"duration": 0.1, "phone": "l_I"}, {"duration": 0.15, "phone": "iy_E"}], "start": 3.23, "startOffset": 60, "word": "fairly"}]}