{"transcript": "The October seven, nineteen sixty-three, issue of the Militant", "words": [{"alignedWord": "the", "case": "success", "end": 0.16, "endOffset": 3, "phones": [{"duration": 0.01, "phone": "dh_B"}, {"duration": 0.01, "phone": "ah_E"}], "start": 0.14, "startOffset": 0, "word": "The"}, {"alignedWord": "october", "case": "success", "end": 0.64, "endOffset": 11, "phones": [{"duration": 0.04, "phone": "aa_B"}, {"duration": 0.09, "phone": "k_I"}, {"duration": 0.08, "phone": "t_I"}, {"duration": 0.11, "phone": "ow_I"}, {"duration": 0.07, "phone": "b_I"}, {"duration": 0.09, "phone": "er_E"}], "start": 0.16, "startOffset": 4, "word": "October"}, {"alignedWord": "seven", "case": "success", "end": 1.1800000000000002, "endOffset": 17, "phones": [{"duration": 0.17, "phone": "s_B"}, {"duration": 0.09, "phone": "eh_I"}, {"duration": 0.05, "phone": "v_I"}, {"duration": 0.08, "phone": "ah_I"}, {"duration": 0.13, "phone": "n_E"}], "start": 0.66, "startOffset": 12, "word": "seven"}, {"alignedWord": "nineteen", "case": "success", "end": 1.65, "endOffset": 27, "phones": [{"duration": 0.02, "phone": "n_B"}, {"duration": 0.12, "phone": "ay_I"}, {"duration": 0.05, "phone": "n_I"}, {"duration": 0.1, "phone": "t_I"}, {"duration": 0.1, "phone": "iy_I"}, {"duration": 0.08, "phone": "n_E"}], "start": 1.18, "startOffset": 19, "word": "nineteen"}, {"alignedWord": "sixty", "case": "success", "end": 2.07, "endOffset": 33, "phones": [{"duration": 0.07, "phone": "s_B"}, {"duration": 0.07, "phone": "ih_I"}, {"duration": 0.07, "phone": "k_I"}, {"duration": 0.03, "phone": "s_I"}, {"duration": 0.09, "phone": "t_I"}, {"duration": 0.09, "phone": "iy_E"}], "start": 1.65, "startOffset": 28, "word": "sixty"}, {"alignedWord": "three", "case": "success", "end": 2.4699999999999998, "endOffset": 39, "phones": [{"duration": 0.1, "phone": "th_B"}, {"duration": 0.09, "phone": "r_I"}, {"duration": 0.21, "phone": "iy_E"}], "start": 2.07, "startOffset": 34, "word": "three"}, {"alignedWord": "issue", "case": "success", "end": 2.85, "endOffset": 46, "phones": [{"duration": 0.08, "phone": "ih_B"}, {"duration": 0.16, "phone": "sh_I"}, {"duration": 0.11, "phone": "uw_E"}], "start": 2.5, "startOffset": 41, "word": "issue"}, {"alignedWord": "of", "case": "success", "end": 2.99, "endOffset": 49, "phones": [{"duration": 0.08, "phone": "ah_B"}, {"duration": 0.06, "phone": "v_E"}], "start": 2.85, "startOffset": 47, "word": "of"}, {"alignedWord": "the", "case": "success", "end": 3.04, "endOffset": 53, "phones": [{"duration": 0.01, "phone": "dh_B"}, {"duration": 0.04, "phone": "ah_E"}], "start": 2.99, "startOffset": 50, "word": "the"}, {"alignedWord": "militant", "case": "success", "end": 3.6799999999999997, "endOffset": 62, "phones": [{"duration": 0.08, "phone": "m_B"}, {"duration": 0.08, "phone": "ih_I"}, {"duration": 0.08, "phone": "l_I"}, {"duration": 0.08, "phone": "ah_I"}, {"duration": 0.05, "phone": "t_I"}, {"duration": 0.1, "phone": "ah_I"}, {"duration": 0.07, "phone": "n_I"}, {"duration": 0.09, "phone": "t_E"}], "start": 3.05, "startOffset": 54, "word": "Militant"}]}