{"transcript": "To the question of, quote, Are you a Communist? End quote, he first answered \"Yes,\"", "words": [{"alignedWord": "to", "case": "success", "end": 0.12, "endOffset": 2, "phones": [{"duration": 0.07, "phone": "t_B"}, {"duration": 0.05, "phone": "uw_E"}], "start": 0.0, "startOffset": 0, "word": "To"}, {"alignedWord": "the", "case": "success", "end": 0.22, "endOffset": 6, "phones": [{"duration": 0.05, "phone": "dh_B"}, {"duration": 0.05, "phone": "ah_E"}], "start": 0.12, "startOffset": 3, "word": "the"}, {"alignedWord": "question", "case": "success", "end": 0.72, "endOffset": 15, "phones": [{"duration": 0.09, "phone": "k_B"}, {"duration": 0.04, "phone": "w_I"}, {"duration": 0.11, "phone": "eh_I"}, {"duration": 0.09, "phone": "s_I"}, {"duration": 0.07, "phone": "ch_I"}, {"duration": 0.05, "phone": "ah_I"}, {"duration": 0.05, "phone": "n_E"}], "start": 0.22, "startOffset": 7, "word": "question"}, {"alignedWord": "of", "case": "success", "end": 0.89, "endOffset": 18, "phones": [{"duration": 0.09, "phone": "ah_B"}, {"duration": 0.08, "phone": "v_E"}], "start": 0.72, "startOffset": 16, "word": "of"}, {"alignedWord": "quote", "case": "success", "end": 1.24, "endOffset": 25, "phones": [{"duration": 0.07, "phone": "k_B"}, {"duration": 0.06, "phone": "w_I"}, {"duration": 0.1, "phone": "ow_I"}, {"duration": 0.12, "phone": "t_E"}], "start": 0.89, "startOffset": 20, "word": "quote"}, {"alignedWord": "are", "case": "success", "end": 1.7, "endOffset": 30, "phones": [{"duration": 0.15, "phone": "aa_B"}, {"duration": 0.09, "phone": "r_E"}], "start": 1.46, "startOffset": 27, "word": "Are"}, {"alignedWord": "you", "case": "success", "end": 1.93, "endOffset": 34, "phones": [{"duration": 0.09, "phone": "y_B"}, {"duration": 0.14, "phone": "uw_E"}], "start": 1.7, "startOffset": 31, "word": "you"}, {"alignedWord": "a", "case": "success", "end": 2.01, "endOffset": 36, "phones": [{"duration": 0.08, "phone": "ah_S"}], "start": 1.93, "startOffset": 35, "word": "a"}, {"alignedWord": "communist", "case": "success", "end": 2.92, "endOffset": 46, "phones": [{"duration": 0.13, "phone": "k_B"}, {"duration": 0.11, "phone": "aa_I"}, {"duration": 0.08, "phone": "m_I"}, {"duration": 0.06, "phone": "y_I"}, {"duration": 0.04, "phone": "ah_I"}, {"duration": 0.05, "phone": "n_I"}, {"duration": 0.13, "phone": "ah_I"}, {"duration": 0.11, "phone": "s_I"}, {"duration": 0.2, "phone": "t_E"}], "start": 2.01, "startOffset": 37, "word": "Communist"}, {"alignedWord": "end", "case": "success", "end": 3.5, "endOffset": 51, "phones": [{"duration": 0.13, "phone": "eh_B"}, {"duration": 0.08, "phone": "n_I"}, {"duration": 0.09, "phone": "d_E"}], "start": 3.2, "startOffset": 48, "word": "End"}, {"alignedWord": "quote", "case": "success", "end": 3.82, "endOffset": 57, "phones": [{"duration": 0.07, "phone": "k_B"}, {"duration": 0.07, "phone": "w_I"}, {"duration": 0.09, "phone": "ow_I"}, {"duration": 0.06, "phone": "t_E"}], "start": 3.53, "startOffset": 52, "word": "quote"}, {"alignedWord": "he", "case": "success", "end": 4.0, "endOffset": 61, "phones": [{"duration": 0.07, "phone": "hh_B"}, {"duration": 0.1, "phone": "iy_E"}], "start": 3.83, "startOffset": 59, "word": "he"}, {"alignedWord": "first", "case": "success", "end": 4.4, "endOffset": 67, "phones": [{"duration": 0.11, "phone": "f_B"}, {"duration": 0.14, "phone": "er_I"}, {"duration": 0.06, "phone": "s_I"}, {"duration": 0.09, "phone": "t_E"}], "start": 4.0, "startOffset": 62, "word": "first"}, {"alignedWord": "answered", "case": "success", "end": 4.880000000000001, "endOffset": 76, "phones": [{"duration": 0.11, "phone": "ae_B"}, {"duration": 0.12, "phone": "n_I"}, {"duration": 0.11, "phone": "s_I"}, {"duration": 0.07, "phone": "er_I"}, {"duration": 0.07, "phone": "d_E"}], "start": 4.4, "startOffset": 68, "word": "answered"}, {"alignedWord": "yes", "case": "success", "end": 5.33, "endOffset": 81, "phones": [{"duration": 0.1, "phone": "y_B"}, {"duration": 0.16, "phone": "eh_I"}, {"duration": 0.19, "phone": "s_E"}], "start": 4.88, "startOffset": 78, "word": "Yes"}]}